{

	"9px" : "9 pixels",
	"10px" : "10 pixels",
	"11px" : "11 pixels",
	"12px" : "12 pixels",
	"13px" : "13 pixels",
	"14px" : "14 pixels",
	"15px" : "15 pixels",
	"16px" : "16 pixels",
	"17px" : "17 pixels",
	"18px" : "18 pixels",
	"19px" : "19 pixels",
	"20px" : "20 pixels",
	"21px" : "21 pixels",
	"22px" : "22 pixels",
	"23px" : "23 pixels",
	"24px" : "24 pixels",
	"25px" : "25 pixels",
	"26px" : "26 pixels",
	"27px" : "27 pixels",
	"28px" : "28 pixels",
	"29px" : "29 pixels",
	"30px" : "30 pixels",
	"31px" : "31 pixels",
	"32px" : "32 pixels",
	"33px" : "33 pixels",
	"34px" : "34 pixels",
	"35px" : "35 pixels",
	"36px" : "36 pixels",
	"37px" : "37 pixels",
	"38px" : "38 pixels",
	"39px" : "39 pixels",
	"40px" : "40 pixels",
	"41px" : "41 pixels",
	"42px" : "42 pixels",
	"43px" : "43 pixels",
	"44px" : "44 pixels",
	"45px" : "45 pixels",
	"46px" : "46 pixels",
	"47px" : "47 pixels",
	"48px" : "48 pixels",
	"49px" : "49 pixels",
	"50px" : "50 pixels",
	"51px" : "51 pixels",
	"52px" : "52 pixels",
	"53px" : "53 pixels",
	"54px" : "54 pixels",
	"55px" : "55 pixels",
	"56px" : "56 pixels",
	"57px" : "57 pixels",
	"58px" : "58 pixels",
	"59px" : "59 pixels",
	"60px" : "60 pixels",
	"61px" : "61 pixels",
	"62px" : "62 pixels",
	"63px" : "63 pixels",
	"64px" : "64 pixels",
	"65px" : "65 pixels",
	"66px" : "66 pixels",
	"67px" : "67 pixels",
	"68px" : "68 pixels",
	"69px" : "69 pixels",
	"70px" : "70 pixels",
	"71px" : "71 pixels",
	"72px" : "72 pixels",
	"73px" : "73 pixels",
	"74px" : "74 pixels",
	"75px" : "75 pixels",
	"76px" : "76 pixels",
	"77px" : "77 pixels",
	"78px" : "78 pixels",
	"79px" : "79 pixels",
	"80px" : "80 pixels",
	"81px" : "81 pixels",
	"82px" : "82 pixels",
	"83px" : "83 pixels",
	"84px" : "84 pixels",
	"85px" : "85 pixels",
	"86px" : "86 pixels",
	"87px" : "87 pixels",
	"88px" : "88 pixels",
	"89px" : "89 pixels",
	"90px" : "90 pixels",
	"91px" : "91 pixels",
	"92px" : "92 pixels",
	"93px" : "93 pixels",
	"94px" : "94 pixels",
	"95px" : "95 pixels",
	"96px" : "96 pixels",
	"97px" : "97 pixels",
	"98px" : "98 pixels",
	"99px" : "99 pixels"
	
}